geoserver_api/__init__.py
geoserver_api/client.py
geoserver_api-0.1.0.dist-info/METADATA
geoserver_api-0.1.0.dist-info/WHEEL
geoserver_api-0.1.0.dist-info/RECORD
