Metadata-Version: 2.1
Name: geoserver-api
Version: 0.1.0
Summary: Python API for configuring and interacting with GeoServer. Wraps around the official HTTP Rest API
Author: Javier Smith
Author-email: javier.smith.dlc@gmail.com
Requires-Python: >=3.10,<3.13
Classifier: Programming Language :: Python :: 3
Classifier: Programming Language :: Python :: 3.10
Classifier: Programming Language :: Python :: 3.11
Classifier: Programming Language :: Python :: 3.12
Requires-Dist: numpy (>=1.26.0,<2.0.0)
Requires-Dist: pandas (>=2.1.1,<3.0.0)
Requires-Dist: requests (>=2.31.0,<3.0.0)
